{
  "_class": "shapePath",
  "booleanOperation": -1,
  "clippingMaskMode": 0,
  "do_objectID": "7F390363-70E9-40B2-A324-36F63876C529",
  "edited": true,
  "exportOptions": {
    "_class": "exportOptions",
    "do_objectID": "AD31099F-3465-470A-93DD-B01C989B4CF7",
    "exportFormats": [
    ],
    "includedLayerIds": [
    ],
    "layerOptions": 0,
    "shouldTrim": false
  },
  "frame": {
    "_class": "rect",
    "constrainProportions": false,
    "do_objectID": "D369251E-87D3-4A25-B42F-8453ABAE5FF7",
    "height": 1.600000000000023,
    "width": 22.39999999999998,
    "x": 0.8000000000000682,
    "y": 17.59999999999997
  },
  "hasClippingMask": false,
  "isClosed": true,
  "isFixedToViewport": false,
  "isFlippedHorizontal": false,
  "isFlippedVertical": false,
  "isLocked": false,
  "isVisible": true,
  "layerListExpandedType": 0,
  "name": "Path",
  "nameIsFixed": false,
  "pointRadiusBehaviour": 1,
  "points": [
    {
      "_class": "curvePoint",
      "cornerRadius": 0,
      "curveFrom": "{0.98400000000000176, 0}",
      "curveMode": 4,
      "curveTo": "{0.9642857142857163, 0}",
      "hasCurveFrom": true,
      "hasCurveTo": false,
      "point": "{0.9642857142857163, 0}"
    },
    {
      "_class": "curvePoint",
      "cornerRadius": 0,
      "curveFrom": "{1, 0.77650000000000896}",
      "curveMode": 2,
      "curveTo": "{1, 0.22400000000000767}",
      "hasCurveFrom": true,
      "hasCurveTo": true,
      "point": "{1, 0.5}"
    },
    {
      "_class": "curvePoint",
      "cornerRadius": 0,
      "curveFrom": "{0.9642857142857163, 1}",
      "curveMode": 4,
      "curveTo": "{0.98400000000000176, 1}",
      "hasCurveFrom": false,
      "hasCurveTo": true,
      "point": "{0.9642857142857163, 1}"
    },
    {
      "_class": "curvePoint",
      "cornerRadius": 0,
      "curveFrom": "{0.015999999999998255, 1}",
      "curveMode": 4,
      "curveTo": "{0.035714285714283721, 1}",
      "hasCurveFrom": true,
      "hasCurveTo": false,
      "point": "{0.035714285714283721, 1}"
    },
    {
      "_class": "curvePoint",
      "cornerRadius": 0,
      "curveFrom": "{0, 0.22400000000000767}",
      "curveMode": 2,
      "curveTo": "{0, 0.77650000000000896}",
      "hasCurveFrom": true,
      "hasCurveTo": true,
      "point": "{0, 0.5}"
    },
    {
      "_class": "curvePoint",
      "cornerRadius": 0,
      "curveFrom": "{0.035714285714283721, 0}",
      "curveMode": 4,
      "curveTo": "{0.015999999999998255, 0}",
      "hasCurveFrom": false,
      "hasCurveTo": true,
      "point": "{0.035714285714283721, 0}"
    }
  ],
  "resizingConstraint": 63,
  "resizingType": 0,
  "rotation": 0,
  "shouldBreakMaskChain": false,
  "style": {
    "_class": "style",
    "do_objectID": "4CA5BA7C-853A-427B-BAA9-57F3A8313549",
    "endMarkerType": 0,
    "miterLimit": 10,
    "startMarkerType": 0,
    "windingRule": 1
  }
}