{
  "_class": "shapePath",
  "booleanOperation": -1,
  "clippingMaskMode": 0,
  "do_objectID": "230FC09A-ED5C-438E-9C2F-F3710E85FC8A",
  "edited": true,
  "exportOptions": {
    "_class": "exportOptions",
    "do_objectID": "788E884A-5FEF-4F0F-A74F-05C6A8F7477B",
    "exportFormats": [
    ],
    "includedLayerIds": [
    ],
    "layerOptions": 0,
    "shouldTrim": false
  },
  "frame": {
    "_class": "rect",
    "constrainProportions": false,
    "do_objectID": "F8F88523-DD54-4C8E-A3D6-A6D3B57B24BA",
    "height": 19.21019999999999,
    "width": 12.80680000000001,
    "x": 0,
    "y": 0
  },
  "hasClippingMask": false,
  "isClosed": true,
  "isFixedToViewport": false,
  "isFlippedHorizontal": false,
  "isFlippedVertical": false,
  "isLocked": false,
  "isVisible": true,
  "layerListExpandedType": 0,
  "name": "Path",
  "nameIsFixed": false,
  "pointRadiusBehaviour": 1,
  "points": [
    {
      "_class": "curvePoint",
      "cornerRadius": 0,
      "curveFrom": "{0.94399850079645264, 0}",
      "curveMode": 4,
      "curveTo": "{0.87500390417590723, 0}",
      "hasCurveFrom": true,
      "hasCurveTo": false,
      "point": "{0.87500390417590723, 0}"
    },
    {
      "_class": "curvePoint",
      "cornerRadius": 0,
      "curveFrom": "{1, 0.083335936117269388}",
      "curveMode": 4,
      "curveTo": "{1, 0.037334332802364978}",
      "hasCurveFrom": false,
      "hasCurveTo": true,
      "point": "{1, 0.083335936117269388}"
    },
    {
      "_class": "curvePoint",
      "cornerRadius": 0,
      "curveFrom": "{1, 0.96266566719763502}",
      "curveMode": 4,
      "curveTo": "{1, 0.91666926945060467}",
      "hasCurveFrom": true,
      "hasCurveTo": false,
      "point": "{1, 0.91666926945060467}"
    },
    {
      "_class": "curvePoint",
      "cornerRadius": 0,
      "curveFrom": "{0.87500390417590723, 1}",
      "curveMode": 4,
      "curveTo": "{0.94399850079645264, 1}",
      "hasCurveFrom": false,
      "hasCurveTo": true,
      "point": "{0.87500390417590723, 1}"
    },
    {
      "_class": "curvePoint",
      "cornerRadius": 0,
      "curveFrom": "{0.31249804791204971, 0.75000260278393704}",
      "curveMode": 1,
      "curveTo": "{0.31249804791204971, 0.75000260278393704}",
      "hasCurveFrom": false,
      "hasCurveTo": false,
      "point": "{0.31249804791204971, 0.75000260278393704}"
    },
    {
      "_class": "curvePoint",
      "cornerRadius": 0,
      "curveFrom": "{0.056001499203551824, 0.75000260278393704}",
      "curveMode": 4,
      "curveTo": "{0.12500390417590834, 0.75000260278393704}",
      "hasCurveFrom": true,
      "hasCurveTo": false,
      "point": "{0.12500390417590834, 0.75000260278393704}"
    },
    {
      "_class": "curvePoint",
      "cornerRadius": 0,
      "curveFrom": "{0, 0.66666666666666474}",
      "curveMode": 4,
      "curveTo": "{0, 0.71266826998157207}",
      "hasCurveFrom": false,
      "hasCurveTo": true,
      "point": "{0, 0.66666666666666474}"
    },
    {
      "_class": "curvePoint",
      "cornerRadius": 0,
      "curveFrom": "{0, 0.28733173001842793}",
      "curveMode": 4,
      "curveTo": "{0, 0.33333333333333237}",
      "hasCurveFrom": true,
      "hasCurveTo": false,
      "point": "{0, 0.33333333333333237}"
    },
    {
      "_class": "curvePoint",
      "cornerRadius": 0,
      "curveFrom": "{0.12500390417590834, 0.25000260278393704}",
      "curveMode": 4,
      "curveTo": "{0.056001499203551824, 0.25000260278393704}",
      "hasCurveFrom": false,
      "hasCurveTo": true,
      "point": "{0.12500390417590834, 0.25000260278393704}"
    },
    {
      "_class": "curvePoint",
      "cornerRadius": 0,
      "curveFrom": "{0.31249804791204971, 0.25000260278393704}",
      "curveMode": 1,
      "curveTo": "{0.31249804791204971, 0.25000260278393704}",
      "hasCurveFrom": false,
      "hasCurveTo": false,
      "point": "{0.31249804791204971, 0.25000260278393704}"
    }
  ],
  "resizingConstraint": 63,
  "resizingType": 0,
  "rotation": 0,
  "shouldBreakMaskChain": false,
  "style": {
    "_class": "style",
    "do_objectID": "432D4522-373E-469D-A0B9-BBAB7297754A",
    "endMarkerType": 0,
    "miterLimit": 10,
    "startMarkerType": 0,
    "windingRule": 1
  }
}