{
  "_class": "group",
  "booleanOperation": -1,
  "clippingMaskMode": 0,
  "do_objectID": "C1C6F5AD-99D0-4BD4-BA04-900935B82248",
  "exportOptions": {
    "_class": "exportOptions",
    "do_objectID": "13BA0ACC-C953-4161-A60F-7EFD48223118",
    "exportFormats": [
    ],
    "includedLayerIds": [
    ],
    "layerOptions": 0,
    "shouldTrim": false
  },
  "frame": {
    "_class": "rect",
    "constrainProportions": false,
    "do_objectID": "F024573B-6520-4438-92B1-D8B37B788FD1",
    "height": 38,
    "width": 344,
    "x": 0,
    "y": 204
  },
  "hasClickThrough": false,
  "hasClippingMask": false,
  "isFixedToViewport": false,
  "isFlippedHorizontal": false,
  "isFlippedVertical": false,
  "isLocked": false,
  "isVisible": true,
  "layerListExpandedType": 0,
  "layers": [
    {
      "class": "group",
      "id": "E397C6C7-CB33-4812-92D8-D74A2119B132"
    },
    {
      "class": "rectangle",
      "id": "EA9881D4-D9E9-42D9-8909-C47A11EEEB42"
    },
    {
      "class": "group",
      "id": "28EA62F0-258A-4167-9B4B-6FCC6BDEB5DF"
    }
  ],
  "name": "_5",
  "nameIsFixed": false,
  "resizingConstraint": 63,
  "resizingType": 0,
  "rotation": 0,
  "shouldBreakMaskChain": false,
  "style": {
    "_class": "style",
    "do_objectID": "2E459E8D-778B-453D-9433-9FC9B2696AA7",
    "endMarkerType": 0,
    "fills": [
      {
        "_class": "fill",
        "color": {
          "_class": "color",
          "alpha": 1,
          "blue": 0,
          "green": 0,
          "red": 0
        },
        "fillType": 0,
        "isEnabled": true,
        "noiseIndex": 0,
        "noiseIntensity": 0,
        "patternFillType": 1,
        "patternTileScale": 1
      }
    ],
    "miterLimit": 10,
    "startMarkerType": 0,
    "windingRule": 1
  }
}