{
  "_class": "shapePath",
  "booleanOperation": -1,
  "clippingMaskMode": 0,
  "do_objectID": "1A7701A0-C13C-4934-BDC4-FD59851185EA",
  "edited": true,
  "exportOptions": {
    "_class": "exportOptions",
    "exportFormats": [
    ],
    "includedLayerIds": [
    ],
    "layerOptions": 0,
    "shouldTrim": false
  },
  "frame": {
    "_class": "rect",
    "constrainProportions": false,
    "height": 3.228031146789441,
    "width": 27.91503171180624,
    "x": 8.098384767439777,
    "y": 53.71532314204409
  },
  "hasClippingMask": false,
  "isClosed": true,
  "isFixedToViewport": false,
  "isFlippedHorizontal": false,
  "isFlippedVertical": false,
  "isLocked": false,
  "isVisible": true,
  "layerListExpandedType": 0,
  "name": "Shape_638-path",
  "nameIsFixed": false,
  "pointRadiusBehaviour": 1,
  "points": [
    {
      "_class": "curvePoint",
      "cornerRadius": 0,
      "curveFrom": "{0.033883727533712632, 0.98865582038938804}",
      "curveMode": 4,
      "curveTo": "{0.34812600846101938, 0.99617280990419355}",
      "hasCurveFrom": true,
      "hasCurveTo": true,
      "point": "{0.052323610004808799, 0.99493366448768061}"
    },
    {
      "_class": "curvePoint",
      "cornerRadius": 0,
      "curveFrom": "{-0.0030323656753235033, 0.60470001325432921}",
      "curveMode": 4,
      "curveTo": "{0.017349892089978499, 0.89488504520222634}",
      "hasCurveFrom": true,
      "hasCurveTo": true,
      "point": "{0.0093360177860705596, 0.75113180378289701}"
    },
    {
      "_class": "curvePoint",
      "cornerRadius": 0,
      "curveFrom": "{0.020201452451181785, 0.094051469328812962}",
      "curveMode": 4,
      "curveTo": "{-0.0031190758082636889, 0.40611662886476257}",
      "hasCurveFrom": true,
      "hasCurveTo": true,
      "point": "{0.0091210798249820001, 0.25888128706147651}"
    },
    {
      "_class": "curvePoint",
      "cornerRadius": 0,
      "curveFrom": "{0.20972984351237822, 0.0088836992738460813}",
      "curveMode": 4,
      "curveTo": "{0.040817213039940223, -0.0051904117637843221}",
      "hasCurveFrom": true,
      "hasCurveTo": true,
      "point": "{0.062855570098392571, 0.00020968135797317129}"
    },
    {
      "_class": "curvePoint",
      "cornerRadius": 0,
      "curveFrom": "{0.50347839034036579, 0.0042369039617109333}",
      "curveMode": 4,
      "curveTo": "{0.3566041169263639, 0.0042369039617109333}",
      "hasCurveFrom": false,
      "hasCurveTo": true,
      "point": "{0.50347839034036579, 0.0042369039617109333}"
    },
    {
      "_class": "curvePoint",
      "cornerRadius": 0,
      "curveFrom": "{0.64963620388404009, 0.02220451250157239}",
      "curveMode": 4,
      "curveTo": "{0.50347839034036579, 0.02220451250157239}",
      "hasCurveFrom": true,
      "hasCurveTo": false,
      "point": "{0.50347839034036579, 0.02220451250157239}"
    },
    {
      "_class": "curvePoint",
      "cornerRadius": 0,
      "curveFrom": "{0.95699284960982689, 0.015157508845236206}",
      "curveMode": 4,
      "curveTo": "{0.7957820764298732, 0.02220451250157239}",
      "hasCurveFrom": true,
      "hasCurveTo": true,
      "point": "{0.94191600797788178, 0.02220451250157239}"
    },
    {
      "_class": "curvePoint",
      "cornerRadius": 0,
      "curveFrom": "{0.99369722722867115, 0.24123530580386024}",
      "curveMode": 2,
      "curveTo": "{0.97174348046223846, 0.06192665809210092}",
      "hasCurveFrom": true,
      "hasCurveTo": true,
      "point": "{0.98272035384545486, 0.1515809819478397}"
    },
    {
      "_class": "curvePoint",
      "cornerRadius": 0,
      "curveFrom": "{1.0003479235897343, 0.63360924253190531}",
      "curveMode": 2,
      "curveTo": "{0.99993836659124113, 0.36591779851969425}",
      "hasCurveFrom": true,
      "hasCurveTo": true,
      "point": "{0.99998508046668422, 0.49648742068313145}"
    },
    {
      "_class": "curvePoint",
      "cornerRadius": 0,
      "curveFrom": "{0.97129757814124795, 0.95671060884460679}",
      "curveMode": 2,
      "curveTo": "{0.99407869532383386, 0.76582238566265293}",
      "hasCurveFrom": true,
      "hasCurveTo": true,
      "point": "{0.98268813673254085, 0.86126649725362991}"
    },
    {
      "_class": "curvePoint",
      "cornerRadius": 0,
      "curveFrom": "{0.6440119939020843, 0.99761847955683902}",
      "curveMode": 4,
      "curveTo": "{0.95581870265696978, 1.0067298316326687}",
      "hasCurveFrom": true,
      "hasCurveTo": true,
      "point": "{0.93998156632801955, 0.99927067344505349}"
    }
  ],
  "resizingConstraint": 63,
  "resizingType": 0,
  "rotation": 0,
  "shouldBreakMaskChain": false,
  "style": {
    "_class": "style",
    "endMarkerType": 0,
    "miterLimit": 10,
    "startMarkerType": 0,
    "windingRule": 1
  }
}