{
  "_class": "shapePath",
  "booleanOperation": -1,
  "clippingMaskMode": 0,
  "do_objectID": "157D3DD9-7B08-46C0-83D1-8E5F0B7FB9EE",
  "edited": true,
  "exportOptions": {
    "_class": "exportOptions",
    "do_objectID": "10F412B0-D438-4B1D-9505-67B5AED64472",
    "exportFormats": [
    ],
    "includedLayerIds": [
    ],
    "layerOptions": 0,
    "shouldTrim": false
  },
  "frame": {
    "_class": "rect",
    "constrainProportions": false,
    "do_objectID": "83237310-3848-4879-BAA1-B81AB6558351",
    "height": 15.99699999999984,
    "width": 9.344102831288566,
    "x": 0.3333300000000037,
    "y": 0
  },
  "hasClippingMask": true,
  "isClosed": true,
  "isFixedToViewport": false,
  "isFlippedHorizontal": false,
  "isFlippedVertical": false,
  "isLocked": false,
  "isVisible": true,
  "layerListExpandedType": 0,
  "name": "Clip 1707",
  "nameIsFixed": false,
  "pointRadiusBehaviour": 1,
  "points": [
    {
      "_class": "curvePoint",
      "cornerRadius": 0,
      "curveFrom": "{0.99447428691434347, 0.47683940738888564}",
      "curveMode": 4,
      "curveTo": "{0.97949157508767148, 0.46808776645621863}",
      "hasCurveFrom": true,
      "hasCurveTo": false,
      "point": "{0.97949157508767148, 0.46808776645621863}"
    },
    {
      "_class": "curvePoint",
      "cornerRadius": 0,
      "curveFrom": "{1.0008954491257751, 0.51147090079390489}",
      "curveMode": 4,
      "curveTo": "{1.0008954491257751, 0.48852909920610932}",
      "hasCurveFrom": true,
      "hasCurveTo": true,
      "point": "{0.99990016898300371, 0.49978120897668121}"
    },
    {
      "_class": "curvePoint",
      "cornerRadius": 0,
      "curveFrom": "{0.97949157508767148, 0.5318497218228494}",
      "curveMode": 4,
      "curveTo": "{0.99447428691434347, 0.52309808089016818}",
      "hasCurveFrom": false,
      "hasCurveTo": true,
      "point": "{0.97949157508767148, 0.5318497218228494}"
    },
    {
      "_class": "curvePoint",
      "cornerRadius": 0,
      "curveFrom": "{0.094730335911546892, 1.0040632618616026}",
      "curveMode": 4,
      "curveTo": "{0.12284111387949198, 0.98781021441520667}",
      "hasCurveFrom": true,
      "hasCurveTo": false,
      "point": "{0.12284111387949198, 0.98781021441520667}"
    },
    {
      "_class": "curvePoint",
      "cornerRadius": 0,
      "curveFrom": "{-0.0070097687474793731, 0.97111958492217332}",
      "curveMode": 4,
      "curveTo": "{0.049211787188410808, 1.0040632618616026}",
      "hasCurveFrom": true,
      "hasCurveTo": true,
      "point": "{0.021029306242438119, 0.98781021441520667}"
    },
    {
      "_class": "curvePoint",
      "cornerRadius": 0,
      "curveFrom": "{0.021029306242438119, 0.92861161467776232}",
      "curveMode": 4,
      "curveTo": "{-0.0070097687474793731, 0.94486466212415809}",
      "hasCurveFrom": false,
      "hasCurveTo": true,
      "point": "{0.021029306242438119, 0.92861161467776232}"
    },
    {
      "_class": "curvePoint",
      "cornerRadius": 0,
      "curveFrom": "{0.82602579823445788, 0.49978120897668121}",
      "curveMode": 1,
      "curveTo": "{0.82602579823445788, 0.49978120897668121}",
      "hasCurveFrom": false,
      "hasCurveTo": false,
      "point": "{0.82602579823445788, 0.49978120897668121}"
    },
    {
      "_class": "curvePoint",
      "cornerRadius": 0,
      "curveFrom": "{-0.0070097687474793731, 0.05513533787585613}",
      "curveMode": 4,
      "curveTo": "{0.021029306242438119, 0.071388385322251918}",
      "hasCurveFrom": true,
      "hasCurveTo": false,
      "point": "{0.021029306242438119, 0.071388385322251918}"
    },
    {
      "_class": "curvePoint",
      "cornerRadius": 0,
      "curveFrom": "{0.049211787188410808, -0.0040632618616025006}",
      "curveMode": 2,
      "curveTo": "{-0.0070097687474793731, 0.02844283303118908}",
      "hasCurveFrom": true,
      "hasCurveTo": true,
      "point": "{0.021029306242438119, 0.012189785584793288}"
    },
    {
      "_class": "curvePoint",
      "cornerRadius": 0,
      "curveFrom": "{0.12284111387949198, 0.012189785584793288}",
      "curveMode": 4,
      "curveTo": "{0.094730335911546892, -0.0040632618616025006}",
      "hasCurveFrom": false,
      "hasCurveTo": true,
      "point": "{0.12284111387949198, 0.012189785584793288}"
    }
  ],
  "resizingConstraint": 63,
  "resizingType": 0,
  "rotation": 0,
  "shouldBreakMaskChain": false,
  "style": {
    "_class": "style",
    "do_objectID": "728FC071-C951-4AC7-A3F2-096769FC2EDF",
    "endMarkerType": 0,
    "miterLimit": 10,
    "startMarkerType": 0,
    "windingRule": 1
  }
}