{
  "_class": "document",
  "assets": {
    "_class": "assetCollection",
    "colors": [
    ],
    "gradients": [
    ],
    "imageCollection": {
      "_class": "imageCollection",
      "images": {
      }
    },
    "images": [
    ]
  },
  "colorSpace": 0,
  "do_objectID": "c7af4c01-d7ca-11e8-8c04-a36e2f861ebb",
  "foreignLayerStyles": [
  ],
  "foreignSymbols": [
  ],
  "foreignTextStyles": [
  ],
  "layerSymbols": {
    "_class": "symbolContainer",
    "objects": [
    ]
  },
  "meta": {
    "appVersion": "52.2",
    "build": 67145,
    "version": 112
  },
  "pages": [
    "Landing",
    "Billing",
    "Pay"
  ],
  "userInfo": {
    "com.invisionlabs.sync": {
      "metadata": "{\"hasSynced\":0,\"hasProjectIdChanged\":0,\"projectId\":0,\"publicLink\":\"\",\"resolution\":2,\"syncAll\":1}"
    }
  }
}