{
  "_class": "text",
  "attributedString": {
    "_class": "attributedString",
    "attributes": [
      {
        "_class": "stringAttribute",
        "attributes": {
          "MSAttributedStringColorAttribute": {
            "_class": "color",
            "alpha": 1,
            "blue": 0.4941176470588236,
            "green": 0.2705882352941179,
            "red": 0.1058823529411765
          },
          "MSAttributedStringFontAttribute": {
            "_class": "fontDescriptor",
            "attributes": {
              "name": "Interstate-ExtraLight",
              "size": 12
            }
          },
          "kerning": 0.3974862,
          "ligature": 0,
          "paragraphStyle": {
            "_class": "paragraphStyle",
            "alignment": 2,
            "allowsDefaultTighteningForTruncation": 0,
            "maximumLineHeight": 16,
            "minimumLineHeight": 16
          }
        },
        "length": 8,
        "location": 0
      }
    ],
    "string": "kWh Used"
  },
  "automaticallyDrawOnUnderlyingPath": false,
  "booleanOperation": -1,
  "clippingMaskMode": 0,
  "do_objectID": "0347B3B7-30CF-4A01-B725-CFD759676E4F",
  "dontSynchroniseWithSymbol": false,
  "exportOptions": {
    "_class": "exportOptions",
    "do_objectID": "7C8B2662-F302-4A8B-8DD0-2F9FFBBFD807",
    "exportFormats": [
    ],
    "includedLayerIds": [
    ],
    "layerOptions": 0,
    "shouldTrim": false
  },
  "frame": {
    "_class": "rect",
    "constrainProportions": false,
    "do_objectID": "1B251D14-0450-463A-9B33-8C6CA2D5FD1E",
    "height": 16,
    "width": 56,
    "x": 16,
    "y": 0
  },
  "glyphBounds": "{{1, 3}, {54, 10}}",
  "hasClippingMask": false,
  "isFixedToViewport": false,
  "isFlippedHorizontal": false,
  "isFlippedVertical": false,
  "isLocked": false,
  "isVisible": true,
  "layerListExpandedType": 0,
  "lineSpacingBehaviour": 2,
  "name": "kWh Used",
  "nameIsFixed": false,
  "resizingConstraint": 47,
  "resizingType": 0,
  "rotation": 0,
  "sharedStyleID": "6A35A88F-35C3-41DA-AA14-4D6006428893",
  "shouldBreakMaskChain": false,
  "style": {
    "_class": "style",
    "do_objectID": "0399EA81-990B-4301-AD85-DD04FCCE9F63",
    "endMarkerType": 0,
    "miterLimit": 10,
    "startMarkerType": 0,
    "textStyle": {
      "_class": "textStyle",
      "do_objectID": "E9E8FFDC-6308-4E4A-85CA-291F5CD1B3E6",
      "encodedAttributes": {
        "MSAttributedStringColorAttribute": {
          "_class": "color",
          "alpha": 1,
          "blue": 0.4941176470588236,
          "green": 0.2705882352941179,
          "red": 0.1058823529411765
        },
        "MSAttributedStringFontAttribute": {
          "_class": "fontDescriptor",
          "attributes": {
            "name": "Interstate-ExtraLight",
            "size": 12
          }
        },
        "kerning": 0.3974862,
        "ligature": 0,
        "paragraphStyle": {
          "_class": "paragraphStyle",
          "alignment": 2,
          "allowsDefaultTighteningForTruncation": 0,
          "maximumLineHeight": 16,
          "minimumLineHeight": 16
        }
      },
      "verticalAlignment": 0
    },
    "windingRule": 1
  },
  "textBehaviour": 0,
  "userInfo": {
    "com.animaapp.stc-sketch-plugin": {
      "kModelPropertiesKey": {
        "isAutoWidth": 1
      }
    }
  }
}