{
  "_class": "shapeGroup",
  "booleanOperation": 0,
  "clippingMaskMode": 0,
  "do_objectID": "74CC3431-8B7B-497D-89E7-26C6C573BD6D",
  "exportOptions": {
    "_class": "exportOptions",
    "do_objectID": "4B1D9284-2801-49BD-9FD7-3683F059F184",
    "exportFormats": [
    ],
    "includedLayerIds": [
    ],
    "layerOptions": 0,
    "shouldTrim": false
  },
  "frame": {
    "_class": "rect",
    "constrainProportions": false,
    "do_objectID": "1E03F6E7-FEEC-4909-8D3E-43F14D961FC8",
    "height": 40,
    "width": 270,
    "x": 0,
    "y": 0
  },
  "hasClickThrough": false,
  "hasClippingMask": true,
  "isFixedToViewport": false,
  "isFlippedHorizontal": false,
  "isFlippedVertical": false,
  "isLocked": false,
  "isVisible": true,
  "layerListExpandedType": 0,
  "layers": [
    {
      "class": "rectangle",
      "id": "DA556309-E9A2-4BDF-BB1E-696A504495D7"
    },
    {
      "class": "rectangle",
      "id": "4BE25AA0-73C1-4856-B00B-F3441464B611"
    },
    {
      "class": "rectangle",
      "id": "48BCDABD-9F3B-4526-93C2-990C961AEE78"
    },
    {
      "class": "rectangle",
      "id": "B19AF4A3-F8A7-4D82-AC18-713A7344E9B4"
    },
    {
      "class": "rectangle",
      "id": "C8E3DB41-E6F1-41B3-96F1-87C17D88AF6D"
    }
  ],
  "name": "Surface",
  "nameIsFixed": true,
  "resizingConstraint": 63,
  "resizingType": 0,
  "rotation": 0,
  "sharedStyleID": "A10C06B0-408C-4CDD-BA04-BDF0CD2F0B47",
  "shouldBreakMaskChain": false,
  "style": {
    "_class": "style",
    "borders": [
      {
        "_class": "border",
        "color": {
          "_class": "color",
          "alpha": 1,
          "blue": 0.4941176470588236,
          "green": 0.2705882352941179,
          "red": 0.1058823529411765
        },
        "fillType": 0,
        "isEnabled": true,
        "position": 1,
        "thickness": 1
      }
    ],
    "do_objectID": "773343F3-E7AE-4733-A63D-238F19A6AD19",
    "endMarkerType": 0,
    "fills": [
      {
        "_class": "fill",
        "color": {
          "_class": "color",
          "alpha": 1,
          "blue": 1,
          "green": 1,
          "red": 1
        },
        "fillType": 0,
        "isEnabled": false,
        "noiseIndex": 0,
        "noiseIntensity": 0,
        "patternFillType": 1,
        "patternTileScale": 1
      }
    ],
    "miterLimit": 10,
    "startMarkerType": 0,
    "windingRule": 0
  },
  "userInfo": {
    "com.animaapp.stc-sketch-plugin": {
      "kModelPropertiesKey": {
      }
    }
  },
  "windingRule": 0
}