{
  "_class": "text",
  "attributedString": {
    "_class": "attributedString",
    "attributes": [
      {
        "_class": "stringAttribute",
        "attributes": {
          "MSAttributedStringColorAttribute": {
            "_class": "color",
            "alpha": 1,
            "blue": 0.4941176470588236,
            "green": 0.2705882352941179,
            "red": 0.1058823529411765
          },
          "MSAttributedStringFontAttribute": {
            "_class": "fontDescriptor",
            "attributes": {
              "name": "Interstate-Regular",
              "size": 16
            }
          },
          "kerning": 0.2839187,
          "ligature": 0,
          "paragraphStyle": {
            "_class": "paragraphStyle",
            "allowsDefaultTighteningForTruncation": 0,
            "maximumLineHeight": 20,
            "minimumLineHeight": 20
          }
        },
        "length": 24,
        "location": 0
      }
    ],
    "string": "Bank of America ****1234"
  },
  "automaticallyDrawOnUnderlyingPath": false,
  "booleanOperation": 0,
  "clippingMaskMode": 0,
  "do_objectID": "8BC5745F-D28F-4453-BB8A-CC79DD6116E7",
  "dontSynchroniseWithSymbol": false,
  "exportOptions": {
    "_class": "exportOptions",
    "do_objectID": "67F86B8D-0AA8-4012-90BF-ADAE445A772A",
    "exportFormats": [
    ],
    "includedLayerIds": [
    ],
    "layerOptions": 0,
    "shouldTrim": false
  },
  "frame": {
    "_class": "rect",
    "constrainProportions": false,
    "do_objectID": "048CDCF5-E845-4040-9E49-C689A31236AB",
    "height": 20,
    "width": 201,
    "x": 3,
    "y": 26
  },
  "glyphBounds": "{{1, 4}, {199, 13}}",
  "hasClippingMask": false,
  "isFixedToViewport": false,
  "isFlippedHorizontal": false,
  "isFlippedVertical": false,
  "isLocked": false,
  "isVisible": true,
  "layerListExpandedType": 0,
  "lineSpacingBehaviour": 2,
  "name": "Subtitle 1",
  "nameIsFixed": true,
  "resizingConstraint": 10,
  "resizingType": 0,
  "rotation": 0,
  "sharedStyleID": "D3059203-0926-40F9-B226-05834AB30619",
  "shouldBreakMaskChain": false,
  "style": {
    "_class": "style",
    "do_objectID": "1031AF7C-DC53-4703-9A80-027DD2E35B8A",
    "endMarkerType": 0,
    "miterLimit": 10,
    "startMarkerType": 0,
    "textStyle": {
      "_class": "textStyle",
      "do_objectID": "B2CA2164-5504-44D0-9731-CDDCE9ED444B",
      "encodedAttributes": {
        "MSAttributedStringColorAttribute": {
          "_class": "color",
          "alpha": 1,
          "blue": 0.4941176470588236,
          "green": 0.2705882352941179,
          "red": 0.1058823529411765
        },
        "MSAttributedStringFontAttribute": {
          "_class": "fontDescriptor",
          "attributes": {
            "name": "Interstate-Regular",
            "size": 16
          }
        },
        "kerning": 0.2839187,
        "ligature": 0,
        "paragraphStyle": {
          "_class": "paragraphStyle",
          "allowsDefaultTighteningForTruncation": 0,
          "maximumLineHeight": 20,
          "minimumLineHeight": 20
        }
      },
      "verticalAlignment": 0
    },
    "windingRule": 1
  },
  "textBehaviour": 0,
  "userInfo": {
    "com.animaapp.stc-sketch-plugin": {
      "kModelPropertiesKey": {
        "isAutoWidth": 1
      }
    }
  }
}