{
  "_class": "shapePath",
  "booleanOperation": 0,
  "clippingMaskMode": 0,
  "do_objectID": "5214D4A8-A78B-44C2-8D60-C28D20BE06E7",
  "edited": true,
  "exportOptions": {
    "_class": "exportOptions",
    "do_objectID": "AB4AC6DA-4603-4921-B4EB-579B55E59710",
    "exportFormats": [
    ],
    "includedLayerIds": [
    ],
    "layerOptions": 0,
    "shouldTrim": false
  },
  "frame": {
    "_class": "rect",
    "constrainProportions": false,
    "do_objectID": "14AF2FE9-042D-40AB-B2A3-C7802794C52B",
    "height": 17.14285714285714,
    "width": 4.340425531914892,
    "x": 17.36170212765949,
    "y": -9.059419880941277e-14
  },
  "hasClippingMask": false,
  "isClosed": true,
  "isFixedToViewport": false,
  "isFlippedHorizontal": false,
  "isFlippedVertical": false,
  "isLocked": false,
  "isVisible": true,
  "layerListExpandedType": 0,
  "name": "Path",
  "nameIsFixed": false,
  "pointRadiusBehaviour": 1,
  "points": [
    {
      "_class": "curvePoint",
      "cornerRadius": 0,
      "curveFrom": "{0.056021421499505245, 0}",
      "curveMode": 4,
      "curveTo": "{0.12503125218765318, 0}",
      "hasCurveFrom": true,
      "hasCurveTo": false,
      "point": "{0.12503125218765318, 0}"
    },
    {
      "_class": "curvePoint",
      "cornerRadius": 0,
      "curveFrom": "{0, 0.027777777777777776}",
      "curveMode": 4,
      "curveTo": "{0, 0.012453611111111072}",
      "hasCurveFrom": false,
      "hasCurveTo": true,
      "point": "{0, 0.027777777777777776}"
    },
    {
      "_class": "curvePoint",
      "cornerRadius": 0,
      "curveFrom": "{0, 0.98759263055555557}",
      "curveMode": 4,
      "curveTo": "{0, 0.97222222222222221}",
      "hasCurveFrom": true,
      "hasCurveTo": false,
      "point": "{0, 0.97222222222222221}"
    },
    {
      "_class": "curvePoint",
      "cornerRadius": 0,
      "curveFrom": "{0.12503125218765318, 1}",
      "curveMode": 4,
      "curveTo": "{0.056021421499505245, 1}",
      "hasCurveFrom": false,
      "hasCurveTo": true,
      "point": "{0.12503125218765318, 1}"
    },
    {
      "_class": "curvePoint",
      "cornerRadius": 0,
      "curveFrom": "{0.94397732841298909, 1}",
      "curveMode": 4,
      "curveTo": "{0.87496749772484117, 1}",
      "hasCurveFrom": true,
      "hasCurveTo": false,
      "point": "{0.87496749772484117, 1}"
    },
    {
      "_class": "curvePoint",
      "cornerRadius": 0,
      "curveFrom": "{1, 0.97222222222222221}",
      "curveMode": 4,
      "curveTo": "{1, 0.98759263055555557}",
      "hasCurveFrom": false,
      "hasCurveTo": true,
      "point": "{1, 0.97222222222222221}"
    },
    {
      "_class": "curvePoint",
      "cornerRadius": 0,
      "curveFrom": "{1, 0.012453611111111072}",
      "curveMode": 4,
      "curveTo": "{1, 0.027777777777777776}",
      "hasCurveFrom": true,
      "hasCurveTo": false,
      "point": "{1, 0.027777777777777776}"
    },
    {
      "_class": "curvePoint",
      "cornerRadius": 0,
      "curveFrom": "{0.87496749772484117, 0}",
      "curveMode": 4,
      "curveTo": "{0.94397732841298909, 0}",
      "hasCurveFrom": false,
      "hasCurveTo": true,
      "point": "{0.87496749772484117, 0}"
    }
  ],
  "resizingConstraint": 63,
  "resizingType": 0,
  "rotation": 0,
  "sharedStyleID": "B44C09E2-1533-4A5E-A92F-6B98A6B02D1A",
  "shouldBreakMaskChain": false,
  "style": {
    "_class": "style",
    "blur": {
      "_class": "blur",
      "center": "{0.5, 0.5}",
      "do_objectID": "4707B3DB-59FA-4830-8477-562FFACC967B",
      "isEnabled": false,
      "motionAngle": 0,
      "radius": 9,
      "saturation": 1,
      "type": 0
    },
    "do_objectID": "BBCC5C89-DDEE-4325-8AE2-C08C05A3BC2F",
    "endMarkerType": 0,
    "fills": [
      {
        "_class": "fill",
        "color": {
          "_class": "color",
          "alpha": 1,
          "blue": 0.4,
          "green": 0.3882352941176471,
          "red": 0.4
        },
        "fillType": 0,
        "isEnabled": true,
        "noiseIndex": 0,
        "noiseIntensity": 0,
        "patternFillType": 1,
        "patternTileScale": 1
      }
    ],
    "miterLimit": 10,
    "startMarkerType": 0,
    "windingRule": 1
  },
  "userInfo": {
    "com.animaapp.stc-sketch-plugin": {
      "kModelPropertiesKey": {
      }
    }
  }
}